MultiscaleEntropy/__init__.py
MultiscaleEntropy/mse.py
MultiscaleEntropy-0.0.1.dist-info/DESCRIPTION.rst
MultiscaleEntropy-0.0.1.dist-info/METADATA
MultiscaleEntropy-0.0.1.dist-info/RECORD
MultiscaleEntropy-0.0.1.dist-info/WHEEL
MultiscaleEntropy-0.0.1.dist-info/metadata.json
MultiscaleEntropy-0.0.1.dist-info/top_level.txt
