Metadata-Version: 2.0
Name: MultiscaleEntropy
Version: 0.0.1
Summary: A Python module to calculate Multiscale  Entropy of a time series.
Home-page: https://github.com/reatank/MultiscaleEntropy
Author: reatank
Author-email: reatank@foxmail.com
License: GNU
Keywords: multiscale entropy,mse
Platform: UNKNOWN
Requires-Dist: numpy (>=1.9.2)
